ppe_match/__init__.py
ppe_match/strategies.py
ppe_match/testing_framework.py
ppe_match/data/README.md
ppe_match/data/anon_distance_matrix.csv
ppe_match/data/anon_donors.csv
ppe_match/data/anon_recipients.csv
ppe_match-0.1.4.dist-info/LICENSE.txt
ppe_match-0.1.4.dist-info/METADATA
ppe_match-0.1.4.dist-info/WHEEL
ppe_match-0.1.4.dist-info/top_level.txt
ppe_match-0.1.4.dist-info/RECORD
