Metadata-Version: 2.1
Name: ppe-match
Version: 0.1.4
Summary: Intuitive framework that allows researchers to implement and test matching methodologies
Home-page: https://github.com/samorani/MatchingPPE
Author: Ram Bala, Michele Samorani, Rohit Jacob
Author-email: rbala@scu.edu, msamorani@scu.edu, rohitjacob92@gmail.com
License: MIT
Keywords: matching,ppe,framework,matcha,frappe
Platform: UNKNOWN
Classifier: Development Status :: 4 - Beta
Classifier: Intended Audience :: Developers
Classifier: Topic :: Software Development :: Build Tools
Classifier: License :: OSI Approved :: MIT License
Classifier: Programming Language :: Python :: 3
Classifier: Programming Language :: Python :: 3.4
Classifier: Programming Language :: Python :: 3.5
Classifier: Programming Language :: Python :: 3.6
Classifier: Programming Language :: Python :: 3.7
Classifier: Programming Language :: Python :: 3.8
Classifier: Programming Language :: Python :: 3.9
License-File: LICENSE.txt
Requires-Dist: pandas
Requires-Dist: numpy
